{
  "INCIDENT_REF": "INCD-486963-f",
  "CREATION_DATE": "2021-01-15T23:15:35",
  "EST_REST_DATE": "2021-01-16T06:00:00+00:00",
  "MAIN_MESSAGE": "There is a power cut affecting the DG9 postcode area of Stranraer. We had no advance warning of this and only became aware of it at 11.15pm. Repairs are taking longer than expected because of ongoing fault investigations into broken overhead line equipment in the area and our team are now working to get your power back on as quickly and as safely as possible by 6am. We will update this message if this information changes. We apologise for the inconvenience and thank you for your patience. This message was updated at 1:50am on 16th January 2021.",
  "TRANSCRIPT": "There is a power cut affecting the DG9 postcode area of Stranraer. We had no advance warning of this and only became aware of it at 11.15pm. Repairs are taking longer than expected because of ongoing fault investigations into broken overhead line equipment in the area and our team are now working to get your power back on as quickly and as safely as possible by 6am. We will update this message if this information changes. We apologise for the inconvenience and thank you for your patience. This message was updated at 1:50am on 16th January 2021.",
  "LOOK_UP_DESCRIPTION": "Awaiting",
  "HISTORIC_FLAG": null,
  "HISTORIC_TIMESTAMP": null,
  "INC_TYPE_ID": "LV",
  "PLANNED_FLAG": "N",
  "POSTCODES": [
    "DG90QA"
  ]
}