{
  "INCIDENT_REF": "INCD-493101-f",
  "CREATION_DATE": "2021-02-14T09:16:20",
  "EST_REST_DATE": "2021-02-14T11:17:53+00:00",
  "MAIN_MESSAGE": "Monitoring systems on our network have alerted us to an unexpected fault affecting a number of customers over a wide area. We apologise for the inconvenience caused, our emergency response teams have been notified and we expect your supply to be restored by 11:30",
  "TRANSCRIPT": "Monitoring systems on our network have alerted us to an unexpected fault affecting a number of customers over a wide area. We apologise for the inconvenience caused, our emergency response teams have been notified and we expect your supply to be restored by 11:30",
  "LOOK_UP_DESCRIPTION": "Awaiting",
  "HISTORIC_FLAG": null,
  "HISTORIC_TIMESTAMP": null,
  "INC_TYPE_ID": "HV_N",
  "PLANNED_FLAG": "N",
  "POSTCODES": [
    "DG46JZ",
    "DG46LA",
    "DG46LF",
    "DG46LG",
    "DG46LQ"
  ]
}