{
  "INCIDENT_REF": "INCD-490371-f",
  "CREATION_DATE": "2021-02-01T16:49:32",
  "EST_REST_DATE": "2021-02-01T19:49:32+00:00",
  "MAIN_MESSAGE": "There is a power cut in the DG11 postcode area of Lockerbie. We had no advance warning of this and only became aware of it at 4.42pm. Our next available engineer will attend site and the team will work to get your power back on as quickly and as safely as possible by 8:00pm. Once they arrive, or when we receive any update regarding the cause, we will be able to provide you with more information. We apologise for the inconvenience and thank you for your patience. This message was updated at 5:03pm on Monday, 01 February 2021",
  "TRANSCRIPT": "There is a power cut in the DG11 postcode area of Lockerbie. We had no advance warning of this and only became aware of it at 4.42pm. Our next available engineer will attend site and the team will work to get your power back on as quickly and as safely as possible by 8:00pm. Once they arrive, or when we receive any update regarding the cause, we will be able to provide you with more information. We apologise for the inconvenience and thank you for your patience. This message was updated at 5:03pm on Monday, 01 February 2021",
  "LOOK_UP_DESCRIPTION": "Awaiting",
  "HISTORIC_FLAG": null,
  "HISTORIC_TIMESTAMP": null,
  "INC_TYPE_ID": "LV",
  "PLANNED_FLAG": "N",
  "POSTCODES": [
    "DG113NB"
  ]
}