{
  "id": "INCD-408984-E",
  "startTime": 1604519400000,
  "etr": 1604525400000,
  "totalOff": 747,
  "confirmedOff": 747,
  "postcodes": [
    "WV3 9PX",
    "WV1 4SX",
    "WV1 4SZ",
    "WV1 4ST",
    "WV3 9QB",
    "WV3 9RD",
    "WV3 9QG",
    "WV3 9RW",
    "WV3 9QU",
    "WV1 4PL",
    "WV3 9NX",
    "WV1 4SY",
    "WV1 4SL",
    "WV1 4SQ",
    "WV3 9PD",
    "WV3 9JX",
    "WV1 4TA",
    "WV1 4PP",
    "WV3 9PB",
    "WV3 9NS",
    "WV1 4PN",
    "WV3 9NZ",
    "WV3 9QA",
    "WV3 9QQ",
    "WV1 4PR",
    "WV3 9QH",
    "WV1 4SP",
    "WV1 4SJ",
    "WV3 9NT",
    "WV3 9QT",
    "WV3 9QZ",
    "WV1 4SA",
    "WV3 9JT",
    "WV3 9NR",
    "WV3 9PA",
    "WV3 9PZ",
    "WV1 4SU",
    "WV3 9NU",
    "WV3 9NY",
    "WV3 9NP",
    "WV3 9JJ",
    "WV1 4TZ",
    "WV1 4PW",
    "WV3 9DU",
    "WV3 9PU",
    "WV3 9DZ",
    "WV1 4SW"
  ],
  "areas": [
    "WV1",
    "WV3"
  ],
  "status": "In Progress",
  "region": "West Midlands",
  "voltage": "HV",
  "planned": false,
  "predictedOff": 0,
  "restored": 960,
  "priorityOff": 154
}