{
  "FaultLabel": "Resolved power cut",
  "Type": "ResolvedFault",
  "Icon": "icon-success",
  "ShowViewOnMapCTA": false,
  "UnderReview": false,
  "AdditionalFaultInfo": "",
  "UpdateInfo": null,
  "CTAs": [],
  "faultNumber": "10653983",
  "multipleFaultNumbers": null,
  "date": "2021-07-03T11:46:53",
  "region": "Hyde",
  "faultType": "Resolved Fault",
  "faultStatus": "Resolved",
  "previousFaultStatus": "Resolved",
  "consumersOff": 0,
  "estimatedTimeOfRestoration": null,
  "estimatedTimeOfRestorationMajority": "2021-07-03T11:46:53",
  "information": "",
  "actualTimeOfRestoration": "2021-07-03T11:46:53",
  "outageCentrePoint": {
    "lat": 53.450451,
    "lng": -2.05909
  },
  "outageLocations": null,
  "AffectedPostcodes": " SK14 2SY, SK14 3DD, SK14 3DE, SK14 3DF",
  "EtrMUnderReview": true,
  "WebTMSFaultType": "TRAN"
}