{
  "FaultLabel": "Resolved power cut",
  "Type": "ResolvedFault",
  "Icon": "icon-success",
  "ShowViewOnMapCTA": false,
  "UnderReview": false,
  "AdditionalFaultInfo": "Good news! The electricity in your area has been restored. The power cut was caused by a third party damaging our underground cable that provides your supply.",
  "UpdateInfo": null,
  "CTAs": [],
  "faultNumber": "10654512",
  "multipleFaultNumbers": null,
  "date": "2021-07-07T20:34:01",
  "region": "Sale",
  "faultType": "Resolved Fault",
  "faultStatus": "Resolved",
  "previousFaultStatus": "Resolved",
  "consumersOff": 0,
  "estimatedTimeOfRestoration": null,
  "estimatedTimeOfRestorationMajority": "2021-07-07T20:34:01",
  "information": "",
  "actualTimeOfRestoration": "2021-07-07T20:34:01",
  "outageCentrePoint": {
    "lat": 53.41556,
    "lng": -2.360427
  },
  "outageLocations": null,
  "AffectedPostcodes": " M33 4GE, M33 4GP, M33 4QP, M33 4QQ, M33 4QX, M33 4SU",
  "EtrMUnderReview": true,
  "WebTMSFaultType": "D/CA"
}