{
  "FaultLabel": "Resolved power cut",
  "Type": "ResolvedFault",
  "Icon": "icon-success",
  "ShowViewOnMapCTA": false,
  "UnderReview": false,
  "AdditionalFaultInfo": "Good news! The power cut in your area caused by an unexpected incident on our high voltage cable has now been resolved.",
  "UpdateInfo": null,
  "CTAs": [],
  "faultNumber": "40808946",
  "multipleFaultNumbers": null,
  "date": "2021-04-07T18:46:04",
  "region": "Rossendale ",
  "faultType": "Resolved Fault",
  "faultStatus": "Resolved",
  "previousFaultStatus": "Resolved",
  "consumersOff": 0,
  "estimatedTimeOfRestoration": "2021-04-08T21:00:00",
  "estimatedTimeOfRestorationMajority": "2021-04-07T18:46:04",
  "information": "",
  "actualTimeOfRestoration": "2021-04-07T18:46:04",
  "outageCentrePoint": {
    "lat": 53.715632,
    "lng": -2.216868
  },
  "outageLocations": null,
  "AffectedPostcodes": " OL13 8RD, BB4 9RY, BB4 9RZ, OL13 8ND, OL13 8NL, OL13 8RE, OL13 8RG, OL13 8OX, OL13 8RF, OL13 8SA, OL13 8NW, OL13 8NN, BB4 9RT, BB4 9SA, BB4 9SB, OL13 8QE, OL13 8QF, OL13 8QR, OL13 8QW, OL13 8QZ, OL13 8RA, OL13 8RB, OL13 8RH, OL13 8EP, BB4 9RX",
  "EtrMUnderReview": false,
  "WebTMSFaultType": "HVFL"
}