{
  "FaultLabel": "Resolved power cut",
  "Type": "ResolvedFault",
  "Icon": "icon-success",
  "ShowViewOnMapCTA": false,
  "UnderReview": false,
  "AdditionalFaultInfo": "Good news! Our engineers have completed the work in your area and the planned power cut has now been restored.",
  "UpdateInfo": null,
  "CTAs": [],
  "faultNumber": "40814045",
  "multipleFaultNumbers": null,
  "date": "2021-05-19T15:26:46",
  "region": "Thornton-Cleveleys",
  "faultType": "Resolved Fault",
  "faultStatus": "Resolved",
  "previousFaultStatus": "Resolved",
  "consumersOff": 0,
  "estimatedTimeOfRestoration": null,
  "estimatedTimeOfRestorationMajority": "2021-05-19T15:26:46",
  "information": "",
  "actualTimeOfRestoration": "2021-05-19T15:26:46",
  "outageCentrePoint": {
    "lat": 53.868667,
    "lng": -3.010567
  },
  "outageLocations": null,
  "AffectedPostcodes": " FY5 5NU, FY5 5HF, FY5 5EA",
  "EtrMUnderReview": true,
  "WebTMSFaultType": "PLAN"
}