{
  "Title": "RH14 Area",
  "Reference": "GS2693",
  "LoggedAtUtc": "/Date(1604449020000)/",
  "EstimatedFaultUpdateTimeUtc": "/Date(-62135596800000)/",
  "EstimatedArrivalOnSiteUtc": "/Date(1604455200000)/",
  "EstimatedRestorationTimeUtc": "/Date(1604462400000)/",
  "FaultType": "LV",
  "Location": {
    "Latitude": 51.02530546532719,
    "Longitude": -0.4539010728290341,
    "DisplayText": "51.025305465327193, -0.45390107282903408"
  },
  "Message": "We’re sorry for the loss of supply. We currently have a fault affecting the areas listed. Our engineers are on site working hard to get the power back on as quickly as they can. If you need more information, please call us on 105 or send us a message on <a href=\"http://m.me/ssencommunity/\">Facebook</a> or Twitter (<a href=\"https://twitter.com/ssencommunity\">@ssencommunity</a>) and quote reference 'GS2693'",
  "AffectedAreas": [
    "RH14 9BF",
    "RH14 9NE",
    "RH14 9NF",
    "RH14 9NJ"
  ],
  "DepotCode": "44",
  "IsDepot": false
}