{
  "Title": "IV2 Area",
  "Reference": "GW4983",
  "LoggedAtUtc": "/Date(1610656800000)/",
  "EstimatedFaultUpdateTimeUtc": "/Date(-62135596800000)/",
  "EstimatedArrivalOnSiteUtc": "/Date(-62135596800000)/",
  "EstimatedRestorationTimeUtc": "/Date(1610668740000)/",
  "FaultType": "HV",
  "Location": {
    "Latitude": 57.489325047439046,
    "Longitude": -4.047905287454595,
    "DisplayText": "57.489325047439046, -4.0479052874545953"
  },
  "Message": "We’re sorry for the loss of supply. We currently have a fault affecting the areas listed. Our engineers are on site working hard to get the power back on as quickly as they can. If you need more information, please call us on 105 or send us a message on <a href=\"http://m.me/ssencommunity/\">Facebook</a> or Twitter (<a href=\"https://twitter.com/ssencommunity\">@ssencommunity</a>) and quote reference 'GW4983'",
  "AffectedAreas": [
    "IV2 5EF",
    "IV2 5EG",
    "IV2 5EY",
    "IV2 5PR"
  ],
  "DepotCode": "41",
  "IsDepot": false
}