{
  "Title": "AB45 Area",
  "Reference": "HA6804",
  "LoggedAtUtc": "/Date(1616600100000)/",
  "EstimatedFaultUpdateTimeUtc": "/Date(-62135596800000)/",
  "EstimatedArrivalOnSiteUtc": "/Date(-62135596800000)/",
  "EstimatedRestorationTimeUtc": "/Date(1616607000000)/",
  "FaultType": "HV",
  "Location": {
    "Latitude": 57.669955907368475,
    "Longitude": -2.7040561032587647,
    "DisplayText": "57.669955907368475, -2.7040561032587647"
  },
  "Message": "We’re sorry for the loss of supply. We currently have a fault affecting the areas listed. Our engineers are on site working hard to get the power back on as quickly as they can. If you need more information, please call us on 105 or send us a message on <a href=\"http://m.me/ssencommunity/\">Facebook</a> or Twitter (<a href=\"https://twitter.com/ssencommunity\">@ssencommunity</a>) and quote reference 'HA6804'",
  "AffectedAreas": [
    "AB45 2QP",
    "AB45 2SB",
    "AB45 2SD",
    "AB45 2XT",
    "AB45 2YD"
  ],
  "DepotCode": "24",
  "IsDepot": false
}