{
  "Title": "OX11 Area",
  "Reference": "HA8957",
  "LoggedAtUtc": "/Date(1617113700000)/",
  "EstimatedFaultUpdateTimeUtc": "/Date(-62135596800000)/",
  "EstimatedArrivalOnSiteUtc": "/Date(-62135596800000)/",
  "EstimatedRestorationTimeUtc": "/Date(1617121800000)/",
  "FaultType": "LV",
  "Location": {
    "Latitude": 51.58514189935455,
    "Longitude": -1.3072044268239151,
    "DisplayText": "51.585141899354547, -1.3072044268239151"
  },
  "Message": "We’re sorry for the loss of supply. We currently have a fault affecting the areas listed. Our engineers are on site working hard to get the power back on as quickly as they can. If you need more information, please call us on 105 or send us a message on <a href=\"http://m.me/ssencommunity/\">Facebook</a> or Twitter (<a href=\"https://twitter.com/ssencommunity\">@ssencommunity</a>) and quote reference 'HA8957'",
  "AffectedAreas": [
    "OX11 0PD",
    "OX11 0PE",
    "OX11 0PT",
    "OX11 0QQ"
  ],
  "DepotCode": "43",
  "IsDepot": false
}