{
  "IncidentReference": "INCD-229705-Z",
  "PanelContentUrl": "/power-cut/map/power-back-on?incidentId=INCD-229705-Z",
  "Steps": [
    {
      "Active": true,
      "Date": "2021-04-08T13:14:01.2",
      "Message": "Update at 13:14 - We can now confirm that all power in the area should be back on. Our engineers turned off the power to safely repair a fault on our underground cables in the NW9 5 area. We know that being without power during the current pandemic can be especially difficult, so we're sorry for the outage. Please rest assured that as key workers, our staff will continue to work around the clock to keep the lights on. If your power isn't on or there's anything you'd like to talk to us about, call us on 08003163105 which is free from landlines and mobiles.",
      "Name": null
    },
    {
      "Active": false,
      "Date": "2021-04-08T12:19:00",
      "Message": "<p>We became aware of a power cut at 12:19. We’re sorry for any disruption this may have caused you. We didn’t know in advance there would be a power cut but now that we know, our teams will do everything they can to get your power back quickly. </p>",
      "Name": "Power cut reported"
    },
    {
      "Active": false,
      "Date": "2021-04-08T12:13:50",
      "Message": "<p>We have engineers on their way. As this is affecting your area, they will not need to attend your property. Rest assured once they arrive, they&rsquo;ll work as quickly as is safely possible to get your power back on.</p>",
      "Name": "Engineers on their way"
    },
    {
      "Active": false,
      "Date": "2021-04-08T12:13:55",
      "Message": "<p>Engineers are now on site, carrying out investigations into the fault. Once they have completed their assessment, they will carry out repairs.</p>",
      "Name": "Engineers investigating and fixing"
    },
    {
      "Active": true,
      "Date": "2021-04-08T13:08:04.49",
      "Message": "<p>All power in the area should be back on. We’re really sorry for any disruption this caused.</p>",
      "Name": "Power restored"
    }
  ],
  "PowerCutType": "Restored",
  "UKPNIncident": {
    "IncidentId": "Z00038149INCD",
    "IncidentReference": "INCD-229705-Z",
    "IncidentCategory": "24",
    "IncidentType": 2,
    "IncidentPriority": 10,
    "StatusId": 5,
    "CreationDateTime": "2021-04-08T12:13:17",
    "RestoredDateTime": "2021-04-08T13:08:04.49",
    "EstimatedRestorationDate": "2021-04-08T13:00:00",
    "PlannedDate": null,
    "ReceivedDate": "2021-04-08T12:19:00",
    "NoCustomerAffected": 0,
    "NoPlannedCustomers": 0,
    "NoCallsReported": 2,
    "Latitude": 0.0,
    "Longitude": 0.0,
    "Resource": {
      "Id": null,
      "Name": "DAN (R5)",
      "EstimatedTimeOfArrival": "0001-01-01T00:00:00",
      "DispatchedDate": "2021-04-08T12:13:50",
      "ArrivalDate": "2021-04-08T12:13:55",
      "StatusId": 6
    },
    "AffectedCustomers": [],
    "Logs": [
      {
        "ActualEventTime": "2021-04-08T13:13:00",
        "CategoryId": 263,
        "TypeId": 0,
        "Comment": "Update at 13:14 - We can now confirm that all power in the area should be back on. Our engineers turned off the power to safely repair a fault on our underground cables in the NW9 5 area. We know that being without power during the current pandemic can be especially difficult, so we're sorry for the outage. Please rest assured that as key workers, our staff will continue to work around the clock to keep the lights on. If your power isn't on or there's anything you'd like to talk to us about, call us on 08003163105 which is free from landlines and mobiles.",
        "LoggedTime": "2021-04-08T13:14:01.2"
      }
    ],
    "PostCodesAffected": [
      "NW9 5"
    ],
    "PostCodesRestored": [
      "NW95QA",
      "NW95QB",
      "NW95QH",
      "NW95QJ",
      "NW95QW",
      "NW95XG"
    ],
    "PostCodesPlanned": [
      "NW95QA",
      "NW95QB",
      "NW95QH",
      "NW95QJ",
      "NW95QW",
      "NW95XG"
    ],
    "CustomersOnSupply": 51,
    "CustomersOffSupply": 0,
    "IncidentTypeName": "Restored",
    "PlannedIncidentReason": "",
    "Scope": null
  },
  "PostcodesRemaining": [
    "NW9 5"
  ],
  "PostcodeData": [
    {
      "Center": {
        "lat": 51.59841,
        "lng": -0.24813
      },
      "Coordinates": [
        {
          "lat": 51.58979,
          "lng": -0.23823
        },
        {
          "lat": 51.59051,
          "lng": -0.24023
        },
        {
          "lat": 51.59059,
          "lng": -0.24026
        },
        {
          "lat": 51.59073,
          "lng": -0.24039
        },
        {
          "lat": 51.59281,
          "lng": -0.24129
        },
        {
          "lat": 51.59318,
          "lng": -0.24236
        },
        {
          "lat": 51.59318,
          "lng": -0.24313
        },
        {
          "lat": 51.59326,
          "lng": -0.24332
        },
        {
          "lat": 51.5937,
          "lng": -0.24486
        },
        {
          "lat": 51.59387,
          "lng": -0.24519
        },
        {
          "lat": 51.59394,
          "lng": -0.24527
        },
        {
          "lat": 51.59455,
          "lng": -0.24672
        },
        {
          "lat": 51.5943,
          "lng": -0.249
        },
        {
          "lat": 51.59406,
          "lng": -0.24965
        },
        {
          "lat": 51.59397,
          "lng": -0.24971
        },
        {
          "lat": 51.59279,
          "lng": -0.24979
        },
        {
          "lat": 51.59264,
          "lng": -0.25029
        },
        {
          "lat": 51.59255,
          "lng": -0.25093
        },
        {
          "lat": 51.59259,
          "lng": -0.25135
        },
        {
          "lat": 51.59263,
          "lng": -0.25147
        },
        {
          "lat": 51.59263,
          "lng": -0.25214
        },
        {
          "lat": 51.59271,
          "lng": -0.2524
        },
        {
          "lat": 51.59286,
          "lng": -0.25265
        },
        {
          "lat": 51.59255,
          "lng": -0.25387
        },
        {
          "lat": 51.5927,
          "lng": -0.25419
        },
        {
          "lat": 51.59275,
          "lng": -0.25489
        },
        {
          "lat": 51.59273,
          "lng": -0.25492
        },
        {
          "lat": 51.59272,
          "lng": -0.25492
        },
        {
          "lat": 51.59197,
          "lng": -0.25605
        },
        {
          "lat": 51.59137,
          "lng": -0.25609
        },
        {
          "lat": 51.59126,
          "lng": -0.25665
        },
        {
          "lat": 51.59212,
          "lng": -0.25755
        },
        {
          "lat": 51.59214,
          "lng": -0.25766
        },
        {
          "lat": 51.59256,
          "lng": -0.25787
        },
        {
          "lat": 51.59286,
          "lng": -0.25793
        },
        {
          "lat": 51.59292,
          "lng": -0.25801
        },
        {
          "lat": 51.59285,
          "lng": -0.25977
        },
        {
          "lat": 51.59305,
          "lng": -0.26001
        },
        {
          "lat": 51.59313,
          "lng": -0.26005
        },
        {
          "lat": 51.59419,
          "lng": -0.26174
        },
        {
          "lat": 51.59437,
          "lng": -0.26151
        },
        {
          "lat": 51.5953,
          "lng": -0.26135
        },
        {
          "lat": 51.59546,
          "lng": -0.26138
        },
        {
          "lat": 51.59616,
          "lng": -0.26231
        },
        {
          "lat": 51.59615,
          "lng": -0.26238
        },
        {
          "lat": 51.59664,
          "lng": -0.26291
        },
        {
          "lat": 51.59702,
          "lng": -0.2629
        },
        {
          "lat": 51.59709,
          "lng": -0.26355
        },
        {
          "lat": 51.59755,
          "lng": -0.26369
        },
        {
          "lat": 51.59797,
          "lng": -0.2629
        },
        {
          "lat": 51.59797,
          "lng": -0.26288
        },
        {
          "lat": 51.59779,
          "lng": -0.26256
        },
        {
          "lat": 51.59819,
          "lng": -0.26091
        },
        {
          "lat": 51.5987,
          "lng": -0.26121
        },
        {
          "lat": 51.59945,
          "lng": -0.26124
        },
        {
          "lat": 51.59869,
          "lng": -0.25947
        },
        {
          "lat": 51.59884,
          "lng": -0.2572
        },
        {
          "lat": 51.59892,
          "lng": -0.25729
        },
        {
          "lat": 51.59981,
          "lng": -0.25752
        },
        {
          "lat": 51.60099,
          "lng": -0.25662
        },
        {
          "lat": 51.60108,
          "lng": -0.25671
        },
        {
          "lat": 51.60112,
          "lng": -0.25678
        },
        {
          "lat": 51.6022,
          "lng": -0.25564
        },
        {
          "lat": 51.60213,
          "lng": -0.25523
        },
        {
          "lat": 51.60252,
          "lng": -0.25467
        },
        {
          "lat": 51.60269,
          "lng": -0.25452
        },
        {
          "lat": 51.60344,
          "lng": -0.25497
        },
        {
          "lat": 51.60362,
          "lng": -0.25527
        },
        {
          "lat": 51.60378,
          "lng": -0.25536
        },
        {
          "lat": 51.60387,
          "lng": -0.25527
        },
        {
          "lat": 51.60404,
          "lng": -0.25451
        },
        {
          "lat": 51.60399,
          "lng": -0.25367
        },
        {
          "lat": 51.60437,
          "lng": -0.25304
        },
        {
          "lat": 51.60501,
          "lng": -0.25321
        },
        {
          "lat": 51.60519,
          "lng": -0.25282
        },
        {
          "lat": 51.60519,
          "lng": -0.25248
        },
        {
          "lat": 51.60503,
          "lng": -0.25195
        },
        {
          "lat": 51.60526,
          "lng": -0.2506
        },
        {
          "lat": 51.60565,
          "lng": -0.25043
        },
        {
          "lat": 51.606,
          "lng": -0.2494
        },
        {
          "lat": 51.60596,
          "lng": -0.24931
        },
        {
          "lat": 51.60602,
          "lng": -0.24812
        },
        {
          "lat": 51.60637,
          "lng": -0.24739
        },
        {
          "lat": 51.60657,
          "lng": -0.24717
        },
        {
          "lat": 51.60652,
          "lng": -0.24686
        },
        {
          "lat": 51.60633,
          "lng": -0.24648
        },
        {
          "lat": 51.60601,
          "lng": -0.24629
        },
        {
          "lat": 51.60588,
          "lng": -0.24586
        },
        {
          "lat": 51.60627,
          "lng": -0.24479
        },
        {
          "lat": 51.60654,
          "lng": -0.24488
        },
        {
          "lat": 51.60716,
          "lng": -0.24332
        },
        {
          "lat": 51.60635,
          "lng": -0.24212
        },
        {
          "lat": 51.60617,
          "lng": -0.24144
        },
        {
          "lat": 51.60513,
          "lng": -0.24121
        },
        {
          "lat": 51.60487,
          "lng": -0.24128
        },
        {
          "lat": 51.60472,
          "lng": -0.24142
        },
        {
          "lat": 51.60315,
          "lng": -0.2394
        },
        {
          "lat": 51.6029,
          "lng": -0.23948
        },
        {
          "lat": 51.60238,
          "lng": -0.23847
        },
        {
          "lat": 51.60195,
          "lng": -0.23814
        },
        {
          "lat": 51.60145,
          "lng": -0.23806
        },
        {
          "lat": 51.60108,
          "lng": -0.23709
        },
        {
          "lat": 51.60073,
          "lng": -0.2369
        },
        {
          "lat": 51.60034,
          "lng": -0.23711
        },
        {
          "lat": 51.59852,
          "lng": -0.23749
        },
        {
          "lat": 51.59821,
          "lng": -0.23799
        },
        {
          "lat": 51.59781,
          "lng": -0.23765
        },
        {
          "lat": 51.59606,
          "lng": -0.23696
        },
        {
          "lat": 51.59558,
          "lng": -0.23726
        },
        {
          "lat": 51.59487,
          "lng": -0.23652
        },
        {
          "lat": 51.59399,
          "lng": -0.23627
        },
        {
          "lat": 51.59369,
          "lng": -0.23632
        },
        {
          "lat": 51.59334,
          "lng": -0.23656
        },
        {
          "lat": 51.59332,
          "lng": -0.23658
        },
        {
          "lat": 51.59273,
          "lng": -0.23701
        },
        {
          "lat": 51.59254,
          "lng": -0.23736
        },
        {
          "lat": 51.59173,
          "lng": -0.23717
        },
        {
          "lat": 51.59069,
          "lng": -0.23633
        },
        {
          "lat": 51.59036,
          "lng": -0.23687
        },
        {
          "lat": 51.58979,
          "lng": -0.23823
        }
      ],
      "Postcode": "NW9 5"
    }
  ],
  "FullPostcodeData": [
    "NW95QA",
    "NW95QB",
    "NW95QH",
    "NW95QJ",
    "NW95QW",
    "NW95XG"
  ],
  "PinLatitude": null,
  "PinLongitude": null,
  "IncidentCategoryCustomerFriendlyDescription": "We had to turn off power in your area so our engineers could safely carry out emergency repairs to the network.",
  "IncidentTypeTBCEstimatedFriendlyDescription": "12:30 - 13:30",
  "ServiceDown": false,
  "ServiceDownUrl": null,
  "Scope": null
}