{
  "IncidentReference": "INCD-261558-J",
  "PanelContentUrl": "/power-cut/map/power-back-on?incidentId=INCD-261558-J",
  "Steps": [
    {
      "Active": false,
      "Date": "2021-05-07T10:00:00",
      "Message": "<p>We became aware of a power cut at 10:00. We’re sorry for any disruption this may have caused you. We didn’t know in advance there would be a power cut but now that we know, our teams will do everything they can to get your power back quickly. </p>",
      "Name": "Power cut reported"
    },
    {
      "Active": false,
      "Date": "2021-05-07T10:10:33",
      "Message": "<p>We have engineers on their way. As this is affecting your area, they will not need to attend your property. Rest assured once they arrive, they&rsquo;ll work as quickly as is safely possible to get your power back on.</p>",
      "Name": "Engineers on their way"
    },
    {
      "Active": false,
      "Date": "2021-05-07T10:49:00",
      "Message": "<p>Engineers are now on site, carrying out investigations into the fault. Once they have completed their assessment, they will carry out repairs.</p>",
      "Name": "Engineers investigating and fixing"
    },
    {
      "Active": true,
      "Date": "2021-05-07T11:44:10.12",
      "Message": "<p>All power in the area should be back on. We’re really sorry for any disruption this caused.</p>",
      "Name": "Power restored"
    }
  ],
  "PowerCutType": "Restored",
  "UKPNIncident": {
    "IncidentId": "J0003fdb6INCD",
    "IncidentReference": "INCD-261558-J",
    "IncidentCategory": "124",
    "IncidentType": 2,
    "IncidentPriority": 10,
    "StatusId": 5,
    "CreationDateTime": "2021-05-07T10:00:52",
    "RestoredDateTime": "2021-05-07T11:44:10.12",
    "EstimatedRestorationDate": null,
    "PlannedDate": null,
    "ReceivedDate": "2021-05-07T10:00:00",
    "NoCustomerAffected": 0,
    "NoPlannedCustomers": 0,
    "NoCallsReported": 2,
    "Latitude": 0.0,
    "Longitude": 0.0,
    "Resource": {
      "Id": null,
      "Name": "JOSHUA",
      "EstimatedTimeOfArrival": "2021-05-07T10:40:00",
      "DispatchedDate": "2021-05-07T10:10:33",
      "ArrivalDate": "2021-05-07T10:49:00",
      "StatusId": 6
    },
    "AffectedCustomers": [],
    "Logs": [],
    "PostCodesAffected": [
      "SW1E 5"
    ],
    "PostCodesRestored": [
      "SW1E5ND",
      "SW1E5NE",
      "UK"
    ],
    "PostCodesPlanned": [
      "SW1E5ND",
      "SW1E5NE",
      "UK"
    ],
    "CustomersOnSupply": 18,
    "CustomersOffSupply": 0,
    "IncidentTypeName": "Restored",
    "PlannedIncidentReason": "",
    "Scope": null
  },
  "PostcodesRemaining": [
    "SW1E 5"
  ],
  "PostcodeData": [
    {
      "Center": {
        "lat": 51.49752,
        "lng": -0.14155
      },
      "Coordinates": [
        {
          "lat": 51.49633,
          "lng": -0.14224
        },
        {
          "lat": 51.49634,
          "lng": -0.14304
        },
        {
          "lat": 51.49655,
          "lng": -0.1433
        },
        {
          "lat": 51.49658,
          "lng": -0.14337
        },
        {
          "lat": 51.49628,
          "lng": -0.14408
        },
        {
          "lat": 51.49611,
          "lng": -0.14427
        },
        {
          "lat": 51.49663,
          "lng": -0.14474
        },
        {
          "lat": 51.49664,
          "lng": -0.14473
        },
        {
          "lat": 51.49673,
          "lng": -0.14418
        },
        {
          "lat": 51.4971,
          "lng": -0.14409
        },
        {
          "lat": 51.49715,
          "lng": -0.14374
        },
        {
          "lat": 51.49752,
          "lng": -0.14357
        },
        {
          "lat": 51.49771,
          "lng": -0.14375
        },
        {
          "lat": 51.49796,
          "lng": -0.1437
        },
        {
          "lat": 51.49816,
          "lng": -0.1436
        },
        {
          "lat": 51.49817,
          "lng": -0.14317
        },
        {
          "lat": 51.49846,
          "lng": -0.1426
        },
        {
          "lat": 51.49876,
          "lng": -0.14321
        },
        {
          "lat": 51.49898,
          "lng": -0.14255
        },
        {
          "lat": 51.49932,
          "lng": -0.14241
        },
        {
          "lat": 51.4992,
          "lng": -0.14212
        },
        {
          "lat": 51.49896,
          "lng": -0.14189
        },
        {
          "lat": 51.49892,
          "lng": -0.14138
        },
        {
          "lat": 51.49894,
          "lng": -0.14126
        },
        {
          "lat": 51.49889,
          "lng": -0.14107
        },
        {
          "lat": 51.49892,
          "lng": -0.14101
        },
        {
          "lat": 51.49891,
          "lng": -0.14096
        },
        {
          "lat": 51.49868,
          "lng": -0.14061
        },
        {
          "lat": 51.49859,
          "lng": -0.14063
        },
        {
          "lat": 51.49865,
          "lng": -0.14014
        },
        {
          "lat": 51.49856,
          "lng": -0.14004
        },
        {
          "lat": 51.49862,
          "lng": -0.13983
        },
        {
          "lat": 51.49827,
          "lng": -0.13947
        },
        {
          "lat": 51.4983,
          "lng": -0.13926
        },
        {
          "lat": 51.4979,
          "lng": -0.13862
        },
        {
          "lat": 51.49745,
          "lng": -0.1393
        },
        {
          "lat": 51.49723,
          "lng": -0.13924
        },
        {
          "lat": 51.49722,
          "lng": -0.13925
        },
        {
          "lat": 51.49678,
          "lng": -0.13911
        },
        {
          "lat": 51.49645,
          "lng": -0.13964
        },
        {
          "lat": 51.49655,
          "lng": -0.14028
        },
        {
          "lat": 51.49633,
          "lng": -0.1404
        },
        {
          "lat": 51.49614,
          "lng": -0.14147
        },
        {
          "lat": 51.49619,
          "lng": -0.1416
        },
        {
          "lat": 51.49641,
          "lng": -0.14201
        },
        {
          "lat": 51.49633,
          "lng": -0.14224
        }
      ],
      "Postcode": "SW1E 5"
    }
  ],
  "FullPostcodeData": [
    "SW1E5ND",
    "SW1E5NE",
    "UK"
  ],
  "PinLatitude": null,
  "PinLongitude": null,
  "IncidentCategoryCustomerFriendlyDescription": "A fault occurred on a piece of our electrical equipment which controls the power to your home.",
  "IncidentTypeTBCEstimatedFriendlyDescription": "To be confirmed",
  "ServiceDown": false,
  "ServiceDownUrl": null,
  "Scope": null
}